pydantic_set_operations/__init__.py
pydantic_set_operations/main.py
pydantic_set_operations-1.1.0.dist-info/LICENSE
pydantic_set_operations-1.1.0.dist-info/METADATA
pydantic_set_operations-1.1.0.dist-info/WHEEL
pydantic_set_operations-1.1.0.dist-info/top_level.txt
pydantic_set_operations-1.1.0.dist-info/RECORD
