Metadata-Version: 2.1
Name: pydantic-set-operations
Version: 1.1.0
Summary: An enhanced version of Pydantic's BaseModel, allowing for advanced model manipulations. (Inspired in TypeScript)
Home-page: https://github.com/P1etrodev/pydantic-set-operations
Author: P1etrodev
Author-email: undefinedpietro@gmail.com
License: MIT
Classifier: License :: OSI Approved :: MIT License
Classifier: Programming Language :: Python :: 3.10
Classifier: Operating System :: OS Independent
Requires-Python: >=3.10
License-File: LICENSE
Requires-Dist: pydantic
Provides-Extra: dev
Requires-Dist: twine; extra == "dev"
